formed/__init__.py
formed/admin.py
formed/form_elements.py
formed/form_fields.py
formed/forms.py
formed/handler.py
formed/models.py
formed/urls.py
formed/views.py
formed/migrations/0001_initial.py
formed/migrations/0002_add_field_finish_title.py
formed/migrations/0003_formsubmission_source.py
formed/migrations/0004_unique_together_formsubmission_notification.py
formed/migrations/0005_formdefinition_confirmation_email_show_summary.py
formed/migrations/0006_formsubmission_source_url.py
formed/migrations/__init__.py
formed/private/scss/formed.scss
formed/private/scss/components/_form-editor.scss
formed/settings/__init__.py
formed/settings/defaults.py
formed/south_migrations/0001_initial.py
formed/south_migrations/0002_auto__add_field_formdefinition_confirmation_email_show_summary.py
formed/south_migrations/__init__.py
formed/static/admin/form_definition/css/formed.css
formed/static/admin/form_definition/img/cogs.svg
formed/static/admin/form_definition/img/file-empty.svg
formed/static/admin/form_definition/img/menu2.svg
formed/static/admin/form_definition/img/pencil.svg
formed/static/admin/form_definition/img/plus.svg
formed/static/admin/form_definition/img/trash.svg
formed/static/admin/form_definition/js/form-definition-field.js
formed/static/admin/form_definition/js/vendor/Sortable-1.4.2.min.js
formed/static/admin/form_definition/js/vendor/vue-1.0.15.js
formed/static/admin/form_definition/js/vendor/vue-1.0.15.min.js
formed/templates/admin/formed/formdefinition/change_form.html
formed/templates/admin/formed/formsubmission/change_form.html
formed/templates/form_definition/finish.html
formed/templates/form_definition/form.html
formed/templates/form_definition/summary.html
formed/templates/form_definition/email/confirmation.html
formed/templates/form_definition/email/confirmation.txt
formed/templates/form_definition/email/notification.html
formed/templates/form_definition/email/notification.txt
formed/templatetags/__init__.py
formed/templatetags/definition_form_tags.py
django_formed-1.0.0.dist-info/LICENSE
django_formed-1.0.0.dist-info/METADATA
django_formed-1.0.0.dist-info/WHEEL
django_formed-1.0.0.dist-info/top_level.txt
django_formed-1.0.0.dist-info/RECORD
