Metadata-Version: 2.1
Name: django-formed
Version: 1.0.0
Summary: A form designer application for Django
Home-page: https://bitbucket.org/frontendr/django-formed
Author: Johan Arensman
Author-email: johan@frontendr.com
License: MIT
Keywords: django forms builder
Platform: OS Independent
Classifier: Development Status :: 4 - Beta
Classifier: Intended Audience :: Developers
Classifier: License :: OSI Approved :: MIT License
Classifier: Operating System :: OS Independent
Classifier: Topic :: Internet :: WWW/HTTP
Classifier: Programming Language :: Python
Classifier: Programming Language :: Python :: 2.7
Classifier: Programming Language :: Python :: 3.5
Classifier: Framework :: Django
Classifier: Framework :: Django :: 1.6
Classifier: Framework :: Django :: 1.7
Classifier: Framework :: Django :: 1.8
Classifier: Framework :: Django :: 1.9
Requires-Dist: Django (<1.9.999,>=1.6.11)
Requires-Dist: jsonfield (<1.1,>=1.0.3)
